dtlpymetrics/__init__.py
dtlpymetrics/__version__.py
dtlpymetrics/dtlpy_scores.py
dtlpymetrics/evaluating/__init__.py
dtlpymetrics/evaluating/models.py
dtlpymetrics/evaluating/tasks.py
dtlpymetrics/scoring/__init__.py
dtlpymetrics/scoring/models.py
dtlpymetrics/scoring/tasks.py
dtlpymetrics/utils/__init__.py
dtlpymetrics/utils/dl_helpers.py
dtlpymetrics/utils/matching.py
dtlpymetrics/utils/plotting.py
dtlpymetrics-1.2.24.dist-info/LICENSE
dtlpymetrics-1.2.24.dist-info/METADATA
dtlpymetrics-1.2.24.dist-info/WHEEL
dtlpymetrics-1.2.24.dist-info/top_level.txt
dtlpymetrics-1.2.24.dist-info/RECORD
