Metadata-Version: 2.1
Name: dtlpymetrics
Version: 1.2.24
Summary: Scoring and metrics app
Author: Dataloop Team
Author-email: yaya.t@dataloop.ai
Classifier: Programming Language :: Python :: 3.7
Classifier: Programming Language :: Python :: 3.8
Classifier: Programming Language :: Python :: 3.9
Classifier: Programming Language :: Python :: 3.10
License-File: LICENSE
Requires-Dist: dtlpy
Requires-Dist: shapely
Requires-Dist: opencv-python
Requires-Dist: matplotlib
Requires-Dist: pandas
Requires-Dist: tqdm
Requires-Dist: seaborn
Requires-Dist: setuptools >=78.1.1
